UncertainPythonSDP/__init__.py
UncertainPythonSDP/Uncertain/Extensions.py
UncertainPythonSDP/Uncertain/Flip.py
UncertainPythonSDP/Uncertain/Gaussian.py
UncertainPythonSDP/Uncertain/MarkovChainMonteCarloSampler.py
UncertainPythonSDP/Uncertain/Sampler.py
UncertainPythonSDP/Uncertain/Uncertaint.py
UncertainPythonSDP/Uncertain/__init__.py
UncertainPythonSDP/UncertainTests/__init__.py
UncertainPythonSDP/UncertainTests/test_GaussianTests.py
UncertainPythonSDP-1.1.3.dist-info/LICENSE
UncertainPythonSDP-1.1.3.dist-info/METADATA
UncertainPythonSDP-1.1.3.dist-info/WHEEL
UncertainPythonSDP-1.1.3.dist-info/top_level.txt
UncertainPythonSDP-1.1.3.dist-info/RECORD
