Metadata-Version: 2.1
Name: UncertainPythonSDP
Version: 1.1.3
Summary: A uncertain Python package
Home-page: https://github.com/dadi-vardhan/UncertainPythonSDP
Author: Vishnu Vardhan Dadi
Author-email: dadivishnuvardhan@gmail.com
License: MIT
Project-URL: Bug Tracker, https://github.com/dadi-vardhan/UncertainPythonSDP
Platform: UNKNOWN
Classifier: Development Status :: 1 - Planning 
Classifier: Intended Audience :: Science/Research
Classifier: License :: OSI Approved :: MIT License
Classifier: Operating System :: POSIX :: Linux
Classifier: Programming Language :: Python :: 2
Classifier: Programming Language :: Python :: 2.7
Classifier: Programming Language :: Python :: 3
Classifier: Programming Language :: Python :: 3.4
Classifier: Programming Language :: Python :: 3.5
Requires-Python: >=3.6
Requires-Dist: scipy
Requires-Dist: numpy
